sigmatcher/__init__.py
sigmatcher/__main__.py
sigmatcher/analysis.py
sigmatcher/cache.py
sigmatcher/cli.py
sigmatcher/definitions.py
sigmatcher/errors.py
sigmatcher/formats.py
sigmatcher/grep.py
sigmatcher/py.typed
sigmatcher/results.py
sigmatcher-1.8.1.dist-info/WHEEL
sigmatcher-1.8.1.dist-info/entry_points.txt
sigmatcher-1.8.1.dist-info/METADATA
sigmatcher-1.8.1.dist-info/RECORD
