Metadata-Version: 2.3
Name: sigmatcher
Version: 1.8.1
Summary: Write signatures to automatically match java classes and methods between versions
Author: Ori Perry
Author-email: Ori Perry <oriori1703@gmail.com>
License: The MIT License (MIT)
Classifier: Topic :: Security
Classifier: Intended Audience :: Developers
Classifier: Intended Audience :: Information Technology
Classifier: Intended Audience :: Science/Research
Classifier: License :: OSI Approved :: MIT License
Classifier: Programming Language :: Python :: 3
Classifier: Programming Language :: Python :: 3 :: Only
Classifier: Programming Language :: Python :: 3.9
Classifier: Programming Language :: Python :: 3.10
Classifier: Programming Language :: Python :: 3.11
Classifier: Programming Language :: Python :: 3.12
Classifier: Programming Language :: Python :: 3.13
Classifier: Programming Language :: Python :: 3.14
Classifier: Operating System :: OS Independent
Classifier: Typing :: Typed
Requires-Dist: typer>=0.12.3
Requires-Dist: pydantic>=2.11,<3
Requires-Dist: pyyaml>=6.0.1,<7
Requires-Dist: platformdirs>=4.2.2,<5
Requires-Dist: packaging>=24.1,<26
Requires-Dist: typing-extensions ; python_full_version < '3.12'
Requires-Dist: sigmatcher[typing] ; extra == 'all'
Requires-Dist: types-pyyaml>=6.0.1,<7 ; extra == 'typing'
Requires-Python: >=3.10
Project-URL: Documentation, https://github.com/oriori1703/sigmatcher#readme
Project-URL: Issues, https://github.com/oriori1703/sigmatcher/issues
Project-URL: Source, https://github.com/oriori1703/sigmatcher
Provides-Extra: all
Provides-Extra: typing
